["{\"name\":\"Fire Drake\",\"cmc\":null,\"colors\":[\"R\"],\"cost\":\"{1}{R}{R}\",\"is_foil\":\"false\",\"market_price\":\"1.22\",\"multiverse_id\":\"1788\",\"quantity\":\"2\",\"rarity\":\"uncommon\",\"set\":\"The Dark\",\"set_id\":\"DRK\",\"subtypes\":[\"Drake\"],\"types\":[\"Creature\"]}", "{\"name\":\"Fissure\",\"cmc\":null,\"colors\":[\"R\"],\"cost\":\"{3}{R}{R}\",\"is_foil\":\"false\",\"market_price\":\"0.19\",\"multiverse_id\":\"1789\",\"quantity\":\"1\",\"rarity\":\"common\",\"set\":\"The Dark\",\"set_id\":\"DRK\",\"subtypes\":[],\"types\":[\"Instant\"]}"]