["{\"name\":\"Giant Growth\",\"cmc\":1,\"colors\":[\"Green\"],\"cost\":\"{G}\",\"is_foil\":\"false\",\"market_price\":0.16,\"multiverse_id\":205224,\"quantity\":\"4\",\"rarity\":\"Common\",\"set\":\"Magic 2011\",\"set_id\":\"M11\",\"subtypes\":[],\"types\":[\"Instant\"]}", "{\"name\":\"Viscera Seer\",\"cmc\":1,\"colors\":[\"Black\"],\"cost\":\"{B}\",\"is_foil\":\"false\",\"market_price\":0.95,\"multiverse_id\":205232,\"quantity\":\"1\",\"rarity\":\"Common\",\"set\":\"Magic 2011\",\"set_id\":\"M11\",\"subtypes\":[\"Vampire\",\"Wizard\"],\"types\":[\"Creature\"]}", "{\"name\":\"Unsummon\",\"cmc\":1,\"colors\":[\"Blue\"],\"cost\":\"{U}\",\"is_foil\":\"false\",\"market_price\":0.15,\"multiverse_id\":208223,\"quantity\":\"1\",\"rarity\":\"Common\",\"set\":\"Magic 2011\",\"set_id\":\"M11\",\"subtypes\":[],\"types\":[\"Instant\"]}", "{\"name\":\"Spined Wurm\",\"cmc\":5,\"colors\":[\"Green\"],\"cost\":\"{4}{G}\",\"is_foil\":\"false\",\"market_price\":0.15,\"multiverse_id\":205123,\"quantity\":\"1\",\"rarity\":\"Common\",\"set\":\"Magic 2011\",\"set_id\":\"M11\",\"subtypes\":[\"Wurm\"],\"types\":[\"Creature\"]}", "{\"name\":\"Prodigal Pyromancer\",\"cmc\":3,\"colors\":[\"Red\"],\"cost\":\"{2}{R}\",\"is_foil\":\"false\",\"market_price\":0.16,\"multiverse_id\":205231,\"quantity\":\"1\",\"rarity\":\"Uncommon\",\"set\":\"Magic 2011\",\"set_id\":\"M11\",\"subtypes\":[\"Human\",\"Wizard\"],\"types\":[\"Creature\"]}", "{\"name\":\"Hornet Sting\",\"cmc\":1,\"colors\":[\"Green\"],\"cost\":\"{G}\",\"is_foil\":\"false\",\"market_price\":0.15,\"multiverse_id\":205050,\"quantity\":\"1\",\"rarity\":\"Common\",\"set\":\"Magic 2011\",\"set_id\":\"M11\",\"subtypes\":[],\"types\":[\"Instant\"]}", "{\"name\":\"Goldenglow Moth\",\"cmc\":1,\"colors\":[\"White\"],\"cost\":\"{W}\",\"is_foil\":\"false\",\"market_price\":0.15,\"multiverse_id\":208295,\"quantity\":\"1\",\"rarity\":\"Common\",\"set\":\"Magic 2011\",\"set_id\":\"M11\",\"subtypes\":[\"Insect\"],\"types\":[\"Creature\"]}", "{\"name\":\"Fog\",\"cmc\":1,\"colors\":[\"Green\"],\"cost\":\"{G}\",\"is_foil\":\"false\",\"market_price\":0.16,\"multiverse_id\":205064,\"quantity\":\"1\",\"rarity\":\"Common\",\"set\":\"Magic 2011\",\"set_id\":\"M11\",\"subtypes\":[],\"types\":[\"Instant\"]}", "{\"name\":\"Berserkers of Blood Ridge\",\"cmc\":5,\"colors\":[\"Red\"],\"cost\":\"{4}{R}\",\"is_foil\":\"false\",\"market_price\":0.15,\"multiverse_id\":205053,\"quantity\":\"1\",\"rarity\":\"Common\",\"set\":\"Magic 2011\",\"set_id\":\"M11\",\"subtypes\":[\"Human\",\"Berserker\"],\"types\":[\"Creature\"]}", "{\"name\":\"Awakener Druid\",\"cmc\":3,\"colors\":[\"Green\"],\"cost\":\"{2}{G}\",\"is_foil\":\"false\",\"market_price\":0.16,\"multiverse_id\":205076,\"quantity\":\"1\",\"rarity\":\"Uncommon\",\"set\":\"Magic 2011\",\"set_id\":\"M11\",\"subtypes\":[\"Human\",\"Druid\"],\"types\":[\"Creature\"]}", "{\"name\":\"Augury Owl\",\"cmc\":2,\"colors\":[\"Blue\"],\"cost\":\"{1}{U}\",\"is_foil\":\"false\",\"market_price\":0.21,\"multiverse_id\":208225,\"quantity\":\"1\",\"rarity\":\"Common\",\"set\":\"Magic 2011\",\"set_id\":\"M11\",\"subtypes\":[\"Bird\"],\"types\":[\"Creature\"]}", "{\"name\":\"Ajani's Mantra\",\"cmc\":2,\"colors\":[\"White\"],\"cost\":\"{1}{W}\",\"is_foil\":\"false\",\"market_price\":0.28,\"multiverse_id\":204987,\"quantity\":\"1\",\"rarity\":\"Common\",\"set\":\"Magic 2011\",\"set_id\":\"M11\",\"subtypes\":[],\"types\":[\"Enchantment\"]}"]