["{\"name\":\"Eyeblight Assassin\",\"cmc\":3,\"colors\":[\"Black\"],\"cost\":\"{2}{B}\",\"is_foil\":\"false\",\"market_price\":0.15,\"multiverse_id\":398535,\"quantity\":\"4\",\"rarity\":\"Common\",\"set\":\"Magic Origins\",\"set_id\":\"ORI\",\"subtypes\":[\"Elf\",\"Assassin\"],\"types\":[\"Creature\"]}", "{\"name\":\"Vine Snare\",\"cmc\":3,\"colors\":[\"Green\"],\"cost\":\"{2}{G}\",\"is_foil\":\"false\",\"market_price\":0.15,\"multiverse_id\":398658,\"quantity\":\"3\",\"rarity\":\"Common\",\"set\":\"Magic Origins\",\"set_id\":\"ORI\",\"subtypes\":[],\"types\":[\"Instant\"]}", "{\"name\":\"Rabid Bloodsucker\",\"cmc\":5,\"colors\":[\"Black\"],\"cost\":\"{4}{B}\",\"is_foil\":\"false\",\"market_price\":0.15,\"multiverse_id\":398557,\"quantity\":\"3\",\"rarity\":\"Common\",\"set\":\"Magic Origins\",\"set_id\":\"ORI\",\"subtypes\":[\"Vampire\"],\"types\":[\"Creature\"]}", "{\"name\":\"Nightsnare\",\"cmc\":4,\"colors\":[\"Black\"],\"cost\":\"{3}{B}\",\"is_foil\":\"false\",\"market_price\":0.15,\"multiverse_id\":398562,\"quantity\":\"3\",\"rarity\":\"Common\",\"set\":\"Magic Origins\",\"set_id\":\"ORI\",\"subtypes\":[],\"types\":[\"Sorcery\"]}", "{\"name\":\"Kytheon's Tactics\",\"cmc\":3,\"colors\":[\"White\"],\"cost\":\"{1}{W}{W}\",\"is_foil\":\"false\",\"market_price\":0.14,\"multiverse_id\":398470,\"quantity\":\"3\",\"rarity\":\"Common\",\"set\":\"Magic Origins\",\"set_id\":\"ORI\",\"subtypes\":[],\"types\":[\"Sorcery\"]}", "{\"name\":\"Infernal Scarring\",\"cmc\":2,\"colors\":[\"Black\"],\"cost\":\"{1}{B}\",\"is_foil\":\"false\",\"market_price\":0.15,\"multiverse_id\":398638,\"quantity\":\"3\",\"rarity\":\"Common\",\"set\":\"Magic Origins\",\"set_id\":\"ORI\",\"subtypes\":[\"Aura\"],\"types\":[\"Enchantment\"]}", "{\"name\":\"Enshrouding Mist\",\"cmc\":1,\"colors\":[\"White\"],\"cost\":\"{W}\",\"is_foil\":\"false\",\"market_price\":0.15,\"multiverse_id\":398654,\"quantity\":\"3\",\"rarity\":\"Common\",\"set\":\"Magic Origins\",\"set_id\":\"ORI\",\"subtypes\":[],\"types\":[\"Instant\"]}", "{\"name\":\"Dark Dabbling\",\"cmc\":3,\"colors\":[\"Black\"],\"cost\":\"{2}{B}\",\"is_foil\":\"false\",\"market_price\":0.16,\"multiverse_id\":398466,\"quantity\":\"3\",\"rarity\":\"Common\",\"set\":\"Magic Origins\",\"set_id\":\"ORI\",\"subtypes\":[],\"types\":[\"Instant\"]}", "{\"name\":\"Akroan Jailer\",\"cmc\":1,\"colors\":[\"White\"],\"cost\":\"{W}\",\"is_foil\":\"false\",\"market_price\":0.15,\"multiverse_id\":398656,\"quantity\":\"3\",\"rarity\":\"Common\",\"set\":\"Magic Origins\",\"set_id\":\"ORI\",\"subtypes\":[\"Human\",\"Soldier\"],\"types\":[\"Creature\"]}", "{\"name\":\"Watercourser\",\"cmc\":3,\"colors\":[\"Blue\"],\"cost\":\"{2}{U}\",\"is_foil\":\"false\",\"market_price\":0.15,\"multiverse_id\":398540,\"quantity\":\"2\",\"rarity\":\"Common\",\"set\":\"Magic Origins\",\"set_id\":\"ORI\",\"subtypes\":[\"Elemental\"],\"types\":[\"Creature\"]}", "{\"name\":\"Undead Servant\",\"cmc\":4,\"colors\":[\"Black\"],\"cost\":\"{3}{B}\",\"is_foil\":\"false\",\"market_price\":0.15,\"multiverse_id\":398484,\"quantity\":\"2\",\"rarity\":\"Common\",\"set\":\"Magic Origins\",\"set_id\":\"ORI\",\"subtypes\":[\"Zombie\"],\"types\":[\"Creature\"]}", "{\"name\":\"Touch of Moonglove\",\"cmc\":1,\"colors\":[\"Black\"],\"cost\":\"{B}\",\"is_foil\":\"false\",\"market_price\":0.14,\"multiverse_id\":398600,\"quantity\":\"2\",\"rarity\":\"Common\",\"set\":\"Magic Origins\",\"set_id\":\"ORI\",\"subtypes\":[],\"types\":[\"Instant\"]}", "{\"name\":\"Titan's Strength\",\"cmc\":1,\"colors\":[\"Red\"],\"cost\":\"{R}\",\"is_foil\":\"false\",\"market_price\":0.16,\"multiverse_id\":398680,\"quantity\":\"2\",\"rarity\":\"Common\",\"set\":\"Magic Origins\",\"set_id\":\"ORI\",\"subtypes\":[],\"types\":[\"Instant\"]}", "{\"name\":\"Timberpack Wolf\",\"cmc\":2,\"colors\":[\"Green\"],\"cost\":\"{1}{G}\",\"is_foil\":\"false\",\"market_price\":0.15,\"multiverse_id\":398445,\"quantity\":\"2\",\"rarity\":\"Common\",\"set\":\"Magic Origins\",\"set_id\":\"ORI\",\"subtypes\":[\"Wolf\"],\"types\":[\"Creature\"]}", "{\"name\":\"Stalwart Aven\",\"cmc\":3,\"colors\":[\"White\"],\"cost\":\"{2}{W}\",\"is_foil\":\"false\",\"market_price\":0.15,\"multiverse_id\":398624,\"quantity\":\"2\",\"rarity\":\"Common\",\"set\":\"Magic Origins\",\"set_id\":\"ORI\",\"subtypes\":[\"Bird\",\"Soldier\"],\"types\":[\"Creature\"]}", "{\"name\":\"Mighty Leap\",\"cmc\":2,\"colors\":[\"White\"],\"cost\":\"{1}{W}\",\"is_foil\":\"false\",\"market_price\":0.15,\"multiverse_id\":398630,\"quantity\":\"2\",\"rarity\":\"Common\",\"set\":\"Magic Origins\",\"set_id\":\"ORI\",\"subtypes\":[],\"types\":[\"Instant\"]}", "{\"name\":\"Hitchclaw Recluse\",\"cmc\":3,\"colors\":[\"Green\"],\"cost\":\"{2}{G}\",\"is_foil\":\"false\",\"market_price\":0.14,\"multiverse_id\":398676,\"quantity\":\"2\",\"rarity\":\"Common\",\"set\":\"Magic Origins\",\"set_id\":\"ORI\",\"subtypes\":[\"Spider\"],\"types\":[\"Creature\"]}", "{\"name\":\"Disperse\",\"cmc\":2,\"colors\":[\"Blue\"],\"cost\":\"{1}{U}\",\"is_foil\":\"false\",\"market_price\":0.14,\"multiverse_id\":398528,\"quantity\":\"2\",\"rarity\":\"Common\",\"set\":\"Magic Origins\",\"set_id\":\"ORI\",\"subtypes\":[],\"types\":[\"Instant\"]}", "{\"name\":\"Deadbridge Shaman\",\"cmc\":3,\"colors\":[\"Black\"],\"cost\":\"{2}{B}\",\"is_foil\":\"false\",\"market_price\":0.15,\"multiverse_id\":398500,\"quantity\":\"2\",\"rarity\":\"Common\",\"set\":\"Magic Origins\",\"set_id\":\"ORI\",\"subtypes\":[\"Elf\",\"Shaman\"],\"types\":[\"Creature\"]}", "{\"name\":\"Cleric of the Forward Order\",\"cmc\":2,\"colors\":[\"White\"],\"cost\":\"{1}{W}\",\"is_foil\":\"false\",\"market_price\":0.14,\"multiverse_id\":398451,\"quantity\":\"2\",\"rarity\":\"Common\",\"set\":\"Magic Origins\",\"set_id\":\"ORI\",\"subtypes\":[\"Human\",\"Cleric\"],\"types\":[\"Creature\"]}", "{\"name\":\"Charging Griffin\",\"cmc\":4,\"colors\":[\"White\"],\"cost\":\"{3}{W}\",\"is_foil\":\"false\",\"market_price\":0.14,\"multiverse_id\":398560,\"quantity\":\"2\",\"rarity\":\"Common\",\"set\":\"Magic Origins\",\"set_id\":\"ORI\",\"subtypes\":[\"Griffin\"],\"types\":[\"Creature\"]}", "{\"name\":\"Auramancer\",\"cmc\":3,\"colors\":[\"White\"],\"cost\":\"{2}{W}\",\"is_foil\":\"false\",\"market_price\":0.14,\"multiverse_id\":398678,\"quantity\":\"2\",\"rarity\":\"Common\",\"set\":\"Magic Origins\",\"set_id\":\"ORI\",\"subtypes\":[\"Human\",\"Wizard\"],\"types\":[\"Creature\"]}", "{\"name\":\"Yeva's Forcemage\",\"cmc\":3,\"colors\":[\"Green\"],\"cost\":\"{2}{G}\",\"is_foil\":\"false\",\"market_price\":0.15,\"multiverse_id\":398424,\"quantity\":\"1\",\"rarity\":\"Common\",\"set\":\"Magic Origins\",\"set_id\":\"ORI\",\"subtypes\":[\"Elf\",\"Shaman\"],\"types\":[\"Creature\"]}", "{\"name\":\"Wild Instincts\",\"cmc\":4,\"colors\":[\"Green\"],\"cost\":\"{3}{G}\",\"is_foil\":\"false\",\"market_price\":0.15,\"multiverse_id\":398508,\"quantity\":\"1\",\"rarity\":\"Common\",\"set\":\"Magic Origins\",\"set_id\":\"ORI\",\"subtypes\":[],\"types\":[\"Sorcery\"]}", "{\"name\":\"Volcanic Rambler\",\"cmc\":6,\"colors\":[\"Red\"],\"cost\":\"{5}{R}\",\"is_foil\":\"false\",\"market_price\":0.15,\"multiverse_id\":398636,\"quantity\":\"1\",\"rarity\":\"Common\",\"set\":\"Magic Origins\",\"set_id\":\"ORI\",\"subtypes\":[\"Elemental\"],\"types\":[\"Creature\"]}", "{\"name\":\"Unholy Hunger\",\"cmc\":5,\"colors\":[\"Black\"],\"cost\":\"{3}{B}{B}\",\"is_foil\":\"false\",\"market_price\":0.15,\"multiverse_id\":398452,\"quantity\":\"1\",\"rarity\":\"Common\",\"set\":\"Magic Origins\",\"set_id\":\"ORI\",\"subtypes\":[],\"types\":[\"Instant\"]}", "{\"name\":\"Titanic Growth\",\"cmc\":2,\"colors\":[\"Green\"],\"cost\":\"{1}{G}\",\"is_foil\":\"false\",\"market_price\":0.13,\"multiverse_id\":398648,\"quantity\":\"1\",\"rarity\":\"Common\",\"set\":\"Magic Origins\",\"set_id\":\"ORI\",\"subtypes\":[],\"types\":[\"Instant\"]}", "{\"name\":\"Shambling Ghoul\",\"cmc\":2,\"colors\":[\"Black\"],\"cost\":\"{1}{B}\",\"is_foil\":\"false\",\"market_price\":0.15,\"multiverse_id\":398552,\"quantity\":\"1\",\"rarity\":\"Common\",\"set\":\"Magic Origins\",\"set_id\":\"ORI\",\"subtypes\":[\"Zombie\"],\"types\":[\"Creature\"]}", "{\"name\":\"Separatist Voidmage\",\"cmc\":4,\"colors\":[\"Blue\"],\"cost\":\"{3}{U}\",\"is_foil\":\"false\",\"market_price\":0.15,\"multiverse_id\":398608,\"quantity\":\"1\",\"rarity\":\"Common\",\"set\":\"Magic Origins\",\"set_id\":\"ORI\",\"subtypes\":[\"Human\",\"Wizard\"],\"types\":[\"Creature\"]}", "{\"name\":\"Send to Sleep\",\"cmc\":2,\"colors\":[\"Blue\"],\"cost\":\"{1}{U}\",\"is_foil\":\"false\",\"market_price\":0.15,\"multiverse_id\":398545,\"quantity\":\"1\",\"rarity\":\"Common\",\"set\":\"Magic Origins\",\"set_id\":\"ORI\",\"subtypes\":[],\"types\":[\"Instant\"]}", "{\"name\":\"Scrapskin Drake\",\"cmc\":3,\"colors\":[\"Blue\"],\"cost\":\"{2}{U}\",\"is_foil\":\"false\",\"market_price\":0.15,\"multiverse_id\":398478,\"quantity\":\"1\",\"rarity\":\"Common\",\"set\":\"Magic Origins\",\"set_id\":\"ORI\",\"subtypes\":[\"Zombie\",\"Drake\"],\"types\":[\"Creature\"]}", "{\"name\":\"Ringwarden Owl\",\"cmc\":5,\"colors\":[\"Blue\"],\"cost\":\"{3}{U}{U}\",\"is_foil\":\"false\",\"market_price\":0.15,\"multiverse_id\":398464,\"quantity\":\"1\",\"rarity\":\"Common\",\"set\":\"Magic Origins\",\"set_id\":\"ORI\",\"subtypes\":[\"Bird\"],\"types\":[\"Creature\"]}", "{\"name\":\"Returned Centaur\",\"cmc\":4,\"colors\":[\"Black\"],\"cost\":\"{3}{B}\",\"is_foil\":\"false\",\"market_price\":0.15,\"multiverse_id\":398468,\"quantity\":\"1\",\"rarity\":\"Common\",\"set\":\"Magic Origins\",\"set_id\":\"ORI\",\"subtypes\":[\"Zombie\",\"Centaur\"],\"types\":[\"Creature\"]}", "{\"name\":\"Reave Soul\",\"cmc\":2,\"colors\":[\"Black\"],\"cost\":\"{1}{B}\",\"is_foil\":\"false\",\"market_price\":0.15,\"multiverse_id\":398591,\"quantity\":\"1\",\"rarity\":\"Common\",\"set\":\"Magic Origins\",\"set_id\":\"ORI\",\"subtypes\":[],\"types\":[\"Sorcery\"]}", "{\"name\":\"Prickleboar\",\"cmc\":5,\"colors\":[\"Red\"],\"cost\":\"{4}{R}\",\"is_foil\":\"false\",\"market_price\":0.14,\"multiverse_id\":398449,\"quantity\":\"1\",\"rarity\":\"Common\",\"set\":\"Magic Origins\",\"set_id\":\"ORI\",\"subtypes\":[\"Boar\"],\"types\":[\"Creature\"]}", "{\"name\":\"Orchard Spirit\",\"cmc\":3,\"colors\":[\"Green\"],\"cost\":\"{2}{G}\",\"is_foil\":\"false\",\"market_price\":0.14,\"multiverse_id\":398644,\"quantity\":\"1\",\"rarity\":\"Common\",\"set\":\"Magic Origins\",\"set_id\":\"ORI\",\"subtypes\":[\"Spirit\"],\"types\":[\"Creature\"]}", "{\"name\":\"Nivix Barrier\",\"cmc\":4,\"colors\":[\"Blue\"],\"cost\":\"{3}{U}\",\"is_foil\":\"false\",\"market_price\":0.15,\"multiverse_id\":398465,\"quantity\":\"1\",\"rarity\":\"Common\",\"set\":\"Magic Origins\",\"set_id\":\"ORI\",\"subtypes\":[\"Illusion\",\"Wall\"],\"types\":[\"Creature\"]}", "{\"name\":\"Nissa's Pilgrimage\",\"cmc\":3,\"colors\":[\"Green\"],\"cost\":\"{2}{G}\",\"is_foil\":\"false\",\"market_price\":0.18,\"multiverse_id\":398593,\"quantity\":\"1\",\"rarity\":\"Common\",\"set\":\"Magic Origins\",\"set_id\":\"ORI\",\"subtypes\":[],\"types\":[\"Sorcery\"]}", "{\"name\":\"Nantuko Husk\",\"cmc\":3,\"colors\":[\"Black\"],\"cost\":\"{2}{B}\",\"is_foil\":\"false\",\"market_price\":0.15,\"multiverse_id\":398440,\"quantity\":\"1\",\"rarity\":\"Common\",\"set\":\"Magic Origins\",\"set_id\":\"ORI\",\"subtypes\":[\"Zombie\",\"Insect\"],\"types\":[\"Creature\"]}", "{\"name\":\"Macabre Waltz\",\"cmc\":2,\"colors\":[\"Black\"],\"cost\":\"{1}{B}\",\"is_foil\":\"false\",\"market_price\":0.15,\"multiverse_id\":398494,\"quantity\":\"1\",\"rarity\":\"Common\",\"set\":\"Magic Origins\",\"set_id\":\"ORI\",\"subtypes\":[],\"types\":[\"Sorcery\"]}", "{\"name\":\"Lightning Javelin\",\"cmc\":4,\"colors\":[\"Red\"],\"cost\":\"{3}{R}\",\"is_foil\":\"false\",\"market_price\":0.14,\"multiverse_id\":398538,\"quantity\":\"1\",\"rarity\":\"Common\",\"set\":\"Magic Origins\",\"set_id\":\"ORI\",\"subtypes\":[],\"types\":[\"Sorcery\"]}", "{\"name\":\"Leaf Gilder\",\"cmc\":2,\"colors\":[\"Green\"],\"cost\":\"{1}{G}\",\"is_foil\":\"false\",\"market_price\":0.14,\"multiverse_id\":398634,\"quantity\":\"1\",\"rarity\":\"Common\",\"set\":\"Magic Origins\",\"set_id\":\"ORI\",\"subtypes\":[\"Elf\",\"Druid\"],\"types\":[\"Creature\"]}", "{\"name\":\"Heavy Infantry\",\"cmc\":5,\"colors\":[\"White\"],\"cost\":\"{4}{W}\",\"is_foil\":\"false\",\"market_price\":0.15,\"multiverse_id\":398408,\"quantity\":\"1\",\"rarity\":\"Common\",\"set\":\"Magic Origins\",\"set_id\":\"ORI\",\"subtypes\":[\"Human\",\"Soldier\"],\"types\":[\"Creature\"]}", "{\"name\":\"Ghirapur Gearcrafter\",\"cmc\":3,\"colors\":[\"Red\"],\"cost\":\"{2}{R}\",\"is_foil\":\"false\",\"market_price\":0.15,\"multiverse_id\":398681,\"quantity\":\"1\",\"rarity\":\"Common\",\"set\":\"Magic Origins\",\"set_id\":\"ORI\",\"subtypes\":[\"Human\",\"Artificer\"],\"types\":[\"Creature\"]}", "{\"name\":\"Elvish Visionary\",\"cmc\":2,\"colors\":[\"Green\"],\"cost\":\"{1}{G}\",\"is_foil\":\"false\",\"market_price\":0.15,\"multiverse_id\":398554,\"quantity\":\"1\",\"rarity\":\"Common\",\"set\":\"Magic Origins\",\"set_id\":\"ORI\",\"subtypes\":[\"Elf\",\"Shaman\"],\"types\":[\"Creature\"]}", "{\"name\":\"Caustic Caterpillar\",\"cmc\":1,\"colors\":[\"Green\"],\"cost\":\"{G}\",\"is_foil\":\"false\",\"market_price\":0.14,\"multiverse_id\":398409,\"quantity\":\"1\",\"rarity\":\"Common\",\"set\":\"Magic Origins\",\"set_id\":\"ORI\",\"subtypes\":[\"Insect\"],\"types\":[\"Creature\"]}", "{\"name\":\"Catacomb Slug\",\"cmc\":5,\"colors\":[\"Black\"],\"cost\":\"{4}{B}\",\"is_foil\":\"false\",\"market_price\":0.14,\"multiverse_id\":398473,\"quantity\":\"1\",\"rarity\":\"Common\",\"set\":\"Magic Origins\",\"set_id\":\"ORI\",\"subtypes\":[\"Slug\"],\"types\":[\"Creature\"]}", "{\"name\":\"Calculated Dismissal\",\"cmc\":3,\"colors\":[\"Blue\"],\"cost\":\"{2}{U}\",\"is_foil\":\"false\",\"market_price\":0.16,\"multiverse_id\":398480,\"quantity\":\"1\",\"rarity\":\"Common\",\"set\":\"Magic Origins\",\"set_id\":\"ORI\",\"subtypes\":[],\"types\":[\"Instant\"]}", "{\"name\":\"Bellows Lizard\",\"cmc\":1,\"colors\":[\"Red\"],\"cost\":\"{R}\",\"is_foil\":\"false\",\"market_price\":0.14,\"multiverse_id\":398439,\"quantity\":\"1\",\"rarity\":\"Common\",\"set\":\"Magic Origins\",\"set_id\":\"ORI\",\"subtypes\":[\"Lizard\"],\"types\":[\"Creature\"]}", "{\"name\":\"Aspiring Aeronaut\",\"cmc\":4,\"colors\":[\"Blue\"],\"cost\":\"{3}{U}\",\"is_foil\":\"false\",\"market_price\":0.14,\"multiverse_id\":398674,\"quantity\":\"1\",\"rarity\":\"Common\",\"set\":\"Magic Origins\",\"set_id\":\"ORI\",\"subtypes\":[\"Human\",\"Artificer\"],\"types\":[\"Creature\"]}", "{\"name\":\"Aerial Volley\",\"cmc\":1,\"colors\":[\"Green\"],\"cost\":\"{G}\",\"is_foil\":\"false\",\"market_price\":0.14,\"multiverse_id\":398565,\"quantity\":\"1\",\"rarity\":\"Common\",\"set\":\"Magic Origins\",\"set_id\":\"ORI\",\"subtypes\":[],\"types\":[\"Instant\"]}", "{\"name\":\"Act of Treason\",\"cmc\":3,\"colors\":[\"Red\"],\"cost\":\"{2}{R}\",\"is_foil\":\"false\",\"market_price\":0.14,\"multiverse_id\":398578,\"quantity\":\"1\",\"rarity\":\"Common\",\"set\":\"Magic Origins\",\"set_id\":\"ORI\",\"subtypes\":[],\"types\":[\"Sorcery\"]}"]